{
  "001400": {
    "jmeno": "Aleš",
    "osloveni": "Ájo",
    "prijmeni": "HRUBÝ",
    "telefon": "737 341 400",
    "email": "hrubyales1@seznam.cz",
    "datum_narozeni": "1997-12-23",
    "spravce": "Ája",
    "budka_cislo": 1,
    "budka_nazev": "Ája"
  },
  "002852": {
    "jmeno": "Květoslava",
    "osloveni": "Květo",
    "prijmeni": "NOVOTNÁ",
    "telefon": "739 578 852",
    "email": "",
    "datum_narozeni": "1946-01-11",
    "spravce": "Květa",
    "budka_cislo": 2,
    "budka_nazev": "Holda"
  },
  "000003": {
    "jmeno": "",
    "osloveni": "",
    "prijmeni": "",
    "telefon": "",
    "email": "",
    "datum_narozeni": "",
    "spravce": "Pavel",
    "budka_cislo": 3,
    "budka_nazev": "Pavel"
  },
  "004112": {
    "jmeno": "Josef",
    "osloveni": "Plíšku",
    "prijmeni": "JENIŠ",
    "telefon": "604 239 112",
    "email": "",
    "datum_narozeni": "1964-02-05",
    "spravce": "",
    "budka_cislo": 4,
    "budka_nazev": ""
  },
  "005484": {
    "jmeno": "Josef",
    "osloveni": "Pepo",
    "prijmeni": "BIBERLE",
    "telefon": "608783484",
    "email": "",
    "datum_narozeni": "",
    "spravce": "Vali + Viki",
    "budka_cislo": 5,
    "budka_nazev": "Vali + Viki"
  },
  "006187": {
    "jmeno": "Jan",
    "osloveni": "Honzo",
    "prijmeni": "RICHTER",
    "telefon": "724976187",
    "email": "richter.j@seznam.cz",
    "datum_narozeni": "1979-05-05",
    "spravce": "Honza",
    "budka_cislo": 6,
    "budka_nazev": "U Badyna"
  },
  "007109": {
    "jmeno": "Jiří",
    "osloveni": "Jirko",
    "prijmeni": "ABRAHAM",
    "telefon": "720 600 109",
    "email": "novohradka@volny.cz",
    "datum_narozeni": "1962-05-07",
    "spravce": "Jirka",
    "budka_cislo": 7,
    "budka_nazev": "Jirka"
  },
  "008666": {
    "jmeno": "Karel",
    "osloveni": "Karle",
    "prijmeni": "FRAJVALD",
    "telefon": "604 677 666",
    "email": "",
    "datum_narozeni": "",
    "spravce": "Karel",
    "budka_cislo": 8,
    "budka_nazev": "Karel"
  },
  "009112": {
    "jmeno": "Josef",
    "osloveni": "Plíšku",
    "prijmeni": "JENIŠ",
    "telefon": "604 239 112",
    "email": "",
    "datum_narozeni": "1952-12-12",
    "spravce": "Plíšek",
    "budka_cislo": 9,
    "budka_nazev": "Plíšek 2"
  },
  "010488": {
    "jmeno": "Jirka",
    "osloveni": "Jirko",
    "prijmeni": "HAVLÍK st.",
    "telefon": "731 589 488",
    "email": "",
    "datum_narozeni": "1952-12-12",
    "spravce": "Jirka",
    "budka_cislo": 10,
    "budka_nazev": ""
  },
  "011506": {
    "jmeno": "Radim",
    "osloveni": "Radime",
    "prijmeni": "HERNYCH",
    "telefon": "776 669 506",
    "email": "radim.hernych@gmail.com",
    "datum_narozeni": "",
    "spravce": "Štěpánek",
    "budka_cislo": 11,
    "budka_nazev": "Štěpánek"
  },
  "012112": {
    "jmeno": "Pepa",
    "osloveni": "Plíšku",
    "prijmeni": "JENIŠ",
    "telefon": "604 239 112",
    "email": "",
    "datum_narozeni": "1964-02-05",
    "spravce": "Plíšek",
    "budka_cislo": 12,
    "budka_nazev": "Plíšek 1"
  },
  "013722": {
    "jmeno": "Viktor",
    "osloveni": "Viktore",
    "prijmeni": "STŘÍBRNÝ",
    "telefon": "723 262 722",
    "email": "",
    "datum_narozeni": "",
    "spravce": "Viktor",
    "budka_cislo": 13,
    "budka_nazev": "Lampoš"
  },
  "014108": {
    "jmeno": "DIANKA",
    "osloveni": "Dianko",
    "prijmeni": "💓",
    "telefon": "775 331 108",
    "email": "dianahauptova@gmail.com",
    "datum_narozeni": "1994-08-11",
    "spravce": "Dia",
    "budka_cislo": 14,
    "budka_nazev": "Dia"
  },
  "015491": {
    "jmeno": "Lukáš",
    "osloveni": "Liky",
    "prijmeni": "VYKYDAL",
    "telefon": "602 356 491",
    "email": "vykydal00@gmail.com",
    "datum_narozeni": "1983-12-29",
    "spravce": "Theodorka",
    "budka_cislo": 15,
    "budka_nazev": "Theodorka"
  },
  "016046": {
    "jmeno": "Kamil",
    "osloveni": "Kamile",
    "prijmeni": "MICHALČÁK",
    "telefon": "777 561 046",
    "email": "kmichalcak@gmail.com",
    "datum_narozeni": "1976-04-14",
    "spravce": "Janek",
    "budka_cislo": 16,
    "budka_nazev": "Janek"
  },
  "017328": {
    "jmeno": "Zdeněk",
    "osloveni": "Zdendo",
    "prijmeni": "DRÁBEK",
    "telefon": "702 230 328",
    "email": "zdendadrabek78@gmail.com",
    "datum_narozeni": "1978-10-06",
    "spravce": "Niki",
    "budka_cislo": 17,
    "budka_nazev": "Niki"
  },
  "018173": {
    "jmeno": "Tomáš",
    "osloveni": "Tome",
    "prijmeni": "KOBELKA",
    "telefon": "777 693 173",
    "email": "",
    "datum_narozeni": "1985-09-07",
    "spravce": "Tomášek",
    "budka_cislo": 18,
    "budka_nazev": "Tomášek"
  },
  "019358": {
    "jmeno": "Pavel",
    "osloveni": "Pavle",
    "prijmeni": "MARTÍNEK",
    "telefon": "737 257 358",
    "email": "pavel.martinek.mart@seznam.cz",
    "datum_narozeni": "1958-04-06",
    "spravce": "Pavel",
    "budka_cislo": 19,
    "budka_nazev": "Pavel"
  },
  "020843": {
    "jmeno": "Ladislav",
    "osloveni": "Laďo",
    "prijmeni": "ŠAFR",
    "telefon": "603 261 843",
    "email": "safrladislavst@gmail.com",
    "datum_narozeni": "1954-04-25",
    "spravce": "Kristýnka + Marie",
    "budka_cislo": 20,
    "budka_nazev": "Kristýnka + Marie"
  },
  "021291": {
    "jmeno": "Miloslav",
    "osloveni": "Slávo",
    "prijmeni": "PAROLEK",
    "telefon": "604 302 291",
    "email": "",
    "datum_narozeni": "",
    "spravce": "ZŠ",
    "budka_cislo": 21,
    "budka_nazev": "ZŠ"
  },
  "022291": {
    "jmeno": "Miloslav",
    "osloveni": "Slávo",
    "prijmeni": "PAROLEK",
    "telefon": "604 302 291",
    "email": "",
    "datum_narozeni": "",
    "spravce": "Sláveček + Anežka",
    "budka_cislo": 22,
    "budka_nazev": "Sláveček+Anežka"
  },
  "023175": {
    "jmeno": "Anna",
    "osloveni": "Aničko",
    "prijmeni": "SEKERKOVÁ",
    "telefon": "603 813 175",
    "email": "sekerka@adosgroup.cz",
    "datum_narozeni": "",
    "spravce": "Ivetka",
    "budka_cislo": 23,
    "budka_nazev": "Ivetka"
  },
  "024966": {
    "jmeno": "Milan",
    "osloveni": "Milane",
    "prijmeni": "HÁNA",
    "telefon": "733121966",
    "email": "",
    "datum_narozeni": "",
    "spravce": "Emily",
    "budka_cislo": 24,
    "budka_nazev": "Emily"
  },
  "025053": {
    "jmeno": "Milena",
    "osloveni": "Mílo",
    "prijmeni": "SCHUPPLEROVÁ",
    "telefon": "725 493 053",
    "email": "milena.schupplerova@vhos.cz",
    "datum_narozeni": "1966-03-21",
    "spravce": "Míla",
    "budka_cislo": 25,
    "budka_nazev": ""
  },
  "026488": {
    "jmeno": "Jirka",
    "osloveni": "Jirko",
    "prijmeni": "HAVLÍK st.",
    "telefon": "731 589 488",
    "email": "",
    "datum_narozeni": "1952-12-12",
    "spravce": "Adam",
    "budka_cislo": 26,
    "budka_nazev": "Adam"
  },
  "027714": {
    "jmeno": "Petr",
    "osloveni": "Peťo",
    "prijmeni": "KOBELKA",
    "telefon": "777 662 714",
    "email": "info@petrkobelka.cz",
    "datum_narozeni": "1984-07-28",
    "spravce": "Péťa",
    "budka_cislo": 27,
    "budka_nazev": "Péťa"
  },
  "028714": {
    "jmeno": "Petr",
    "osloveni": "Peťo",
    "prijmeni": "KOBELKA",
    "telefon": "777 662 714",
    "email": "info@petrkobelka.cz",
    "datum_narozeni": "1984-07-28",
    "spravce": "Kristýnka",
    "budka_cislo": 28,
    "budka_nazev": "Kristýnka"
  },
  "029109": {
    "jmeno": "Jiří",
    "osloveni": "Jirko",
    "prijmeni": "ABRAHAM",
    "telefon": "720 600 109",
    "email": "novohradka@volny.cz",
    "datum_narozeni": "1962-05-07",
    "spravce": "Laura",
    "budka_cislo": 29,
    "budka_nazev": "Laura"
  },
  "030424": {
    "jmeno": "Petr",
    "osloveni": "Péťo",
    "prijmeni": "POPPEL",
    "telefon": "603 854 424",
    "email": "petr.poppel@plastikapipes.cz",
    "datum_narozeni": "1972-05-02",
    "spravce": "Péťa",
    "budka_cislo": 30,
    "budka_nazev": "Péťa"
  },
  "031859": {
    "jmeno": "Lubor",
    "osloveni": "Lubore",
    "prijmeni": "BENEŠ",
    "telefon": "602 270 859",
    "email": "benes@buildingexpert.cz",
    "datum_narozeni": "1963-01-09",
    "spravce": "Lubor",
    "budka_cislo": 31,
    "budka_nazev": "Lubor"
  },
  "032625": {
    "jmeno": "Karel",
    "osloveni": "Karle",
    "prijmeni": "PELANT",
    "telefon": "602 305 625",
    "email": "pelantkarel@seznam.cz",
    "datum_narozeni": "1966-12-11",
    "spravce": "Karel",
    "budka_cislo": 32,
    "budka_nazev": "Karel"
  },
  "033755": {
    "jmeno": "Dobroš",
    "osloveni": "Dobro",
    "prijmeni": "CRHA",
    "telefon": "737 261 755",
    "email": "dobros.dc@gmail.com",
    "datum_narozeni": "1973-07-07",
    "spravce": "Dobroš",
    "budka_cislo": 33,
    "budka_nazev": "Crhuš"
  },
  "000034": {
    "jmeno": "",
    "osloveni": "",
    "prijmeni": "",
    "telefon": "",
    "email": "",
    "datum_narozeni": "",
    "spravce": "Adík",
    "budka_cislo": 34,
    "budka_nazev": "Adík"
  },
  "035051": {
    "jmeno": "Miroslav",
    "osloveni": "Miro",
    "prijmeni": "ŠOLTÉS",
    "telefon": "944 356 051",
    "email": "miroslav@soltes.eu",
    "datum_narozeni": "",
    "spravce": "Miro",
    "budka_cislo": 35,
    "budka_nazev": "Miro"
  },
  "036421": {
    "jmeno": "Petr",
    "osloveni": "P/eťo",
    "prijmeni": "HAUPT",
    "telefon": "777430421",
    "email": "hpetrr@email.cz",
    "datum_narozeni": "1987-06-27",
    "spravce": "Peťa",
    "budka_cislo": 36,
    "budka_nazev": "Hauptík"
  },
  "037897": {
    "jmeno": "Stanislav",
    "osloveni": "Staňo",
    "prijmeni": "SCHAFFER",
    "telefon": "605 484 897",
    "email": "",
    "datum_narozeni": "",
    "spravce": "Standa",
    "budka_cislo": 37,
    "budka_nazev": ""
  },
  "038812": {
    "jmeno": "Pavel",
    "osloveni": "Pavle",
    "prijmeni": "LANGER",
    "telefon": "737 800 812",
    "email": "",
    "datum_narozeni": "1964-01-20",
    "spravce": "Pavel",
    "budka_cislo": 38,
    "budka_nazev": "Vojtík"
  },
  "039508": {
    "jmeno": "Luboš",
    "osloveni": "Lubore",
    "prijmeni": "ŽÁČEK",
    "telefon": "602 356 508",
    "email": "zacek.lubomir@gmail.com",
    "datum_narozeni": "1976-06-24",
    "spravce": "děti MŠ",
    "budka_cislo": 39,
    "budka_nazev": "Mateřská škola"
  },
  "040779": {
    "jmeno": "Lucie",
    "osloveni": "Lucko",
    "prijmeni": "KOBELKOVÁ",
    "telefon": "777 790 779",
    "email": "",
    "datum_narozeni": "1983-02-07",
    "spravce": "pan správce",
    "budka_cislo": 40,
    "budka_nazev": "Lucka"
  },
  "041843": {
    "jmeno": "Ladislav",
    "osloveni": "Laďo",
    "prijmeni": "ŠAFR",
    "telefon": "603 261 843",
    "email": "safrladislavst@gmail.com",
    "datum_narozeni": "1954-04-25",
    "spravce": "Laďa",
    "budka_cislo": 41,
    "budka_nazev": "Laďa"
  },
  "042335": {
    "jmeno": "Milan",
    "osloveni": "Milane",
    "prijmeni": "LINDOVSKÝ",
    "telefon": "602 735 335",
    "email": "",
    "datum_narozeni": "1956-03-28",
    "spravce": "",
    "budka_cislo": 42,
    "budka_nazev": ""
  },
  "043471": {
    "jmeno": "Jan",
    "osloveni": "Honzo",
    "prijmeni": "RADA",
    "telefon": "602 356 471",
    "email": "jan.rada.009@gmail.com",
    "datum_narozeni": "1979-01-09",
    "spravce": "",
    "budka_cislo": 43,
    "budka_nazev": "Anežka"
  },
  "044221": {
    "jmeno": "Martina",
    "osloveni": "Marti",
    "prijmeni": "ŠMERÁKOVÁ",
    "telefon": "777 116 221",
    "email": "",
    "datum_narozeni": "1979-04-17",
    "spravce": "Ota",
    "budka_cislo": 44,
    "budka_nazev": ""
  },
  "045358": {
    "jmeno": "Pavel",
    "osloveni": "Pavle",
    "prijmeni": "MARTÍNEK",
    "telefon": "737 257 358",
    "email": "pavel.martinek.mart@seznam.cz",
    "datum_narozeni": "1958-04-06",
    "spravce": "",
    "budka_cislo": 45,
    "budka_nazev": ""
  },
  "046337": {
    "jmeno": "Robin",
    "osloveni": "Robe",
    "prijmeni": "ŠMERÁK",
    "telefon": "775 766 337",
    "email": "",
    "datum_narozeni": "",
    "spravce": "",
    "budka_cislo": 46,
    "budka_nazev": "Hela"
  },
  "047496": {
    "jmeno": "Petr",
    "osloveni": "Peťo",
    "prijmeni": "KOBELKA",
    "telefon": "602356496",
    "email": "",
    "datum_narozeni": "",
    "spravce": "admin",
    "budka_cislo": 47,
    "budka_nazev": "",
    "budky": [
      { "cislo": 47, "nazev": "" },
      { "cislo": 55, "nazev": "" },
      { "cislo": 57, "nazev": "" }
    ]
  },
  "048173": {
    "jmeno": "Tomášek",
    "osloveni": "Tome",
    "prijmeni": "",
    "telefon": "777 693 173",
    "email": "",
    "datum_narozeni": "1985-09-07",
    "spravce": "",
    "budka_cislo": 48,
    "budka_nazev": "U Kapličky"
  },
  "049803": {
    "jmeno": "Josef",
    "osloveni": "Pepo",
    "prijmeni": "TRČKA",
    "telefon": "773 625 803",
    "email": "",
    "datum_narozeni": "",
    "spravce": "",
    "budka_cislo": 49,
    "budka_nazev": "Jonášek"
  },
  "050280": {
    "jmeno": "Jan",
    "osloveni": "Honzo",
    "prijmeni": "PILNÝ",
    "telefon": "602 536 280",
    "email": "info@pipetrade.cz",
    "datum_narozeni": "",
    "spravce": "",
    "budka_cislo": 50,
    "budka_nazev": "Janek"
  },
  "051109": {
    "jmeno": "Jiří",
    "osloveni": "Jirko",
    "prijmeni": "ABRAHAM",
    "telefon": "720 600 109",
    "email": "novohradka@volny.cz",
    "datum_narozeni": "1962-05-07",
    "spravce": "",
    "budka_cislo": 51,
    "budka_nazev": "Ester"
  },
  "052188": {
    "jmeno": "Tomáš",
    "osloveni": "Tome",
    "prijmeni": "KUHN",
    "telefon": "605 238 188",
    "email": "",
    "datum_narozeni": "",
    "spravce": "Tomáš",
    "budka_cislo": 52,
    "budka_nazev": "U Sojky"
  },
  "053182": {
    "jmeno": "Pavel",
    "osloveni": "Pavle",
    "prijmeni": "VYROUBAL",
    "telefon": "603 545 182",
    "email": "",
    "datum_narozeni": "1953-12-09",
    "spravce": "Standa",
    "budka_cislo": 53,
    "budka_nazev": ""
  },
  "054595": {
    "jmeno": "Zdeněk",
    "osloveni": "Zdenku",
    "prijmeni": "VÁVRA",
    "telefon": "777 722 595",
    "email": "info@hotelvinohrad.cz",
    "datum_narozeni": "",
    "spravce": "",
    "budka_cislo": 54,
    "budka_nazev": "Šidlenka"
  },
  "055496": {
    "jmeno": "Petr",
    "osloveni": "Peťo",
    "prijmeni": "KOBELKA",
    "telefon": "602356496",
    "email": "",
    "datum_narozeni": "",
    "spravce": "admin",
    "budka_cislo": 55,
    "budka_nazev": ""
  },
  "056724": {
    "jmeno": "Dušan",
    "osloveni": "Dušo",
    "prijmeni": "DRÁPAL",
    "telefon": "602 570 724",
    "email": "drapal.dusan@seznam.cz",
    "datum_narozeni": "",
    "spravce": "Dušan",
    "budka_cislo": 56,
    "budka_nazev": ""
  },
  "057496": {
    "jmeno": "Petr",
    "osloveni": "Peťa",
    "prijmeni": "KOBELKA",
    "telefon": "602356496",
    "email": "",
    "datum_narozeni": "",
    "spravce": "admin",
    "budka_cislo": 57,
    "budka_nazev": ""
  },
  "058877": {
    "jmeno": "Věra",
    "osloveni": "Věro",
    "prijmeni": "RÉDOVÁ",
    "telefon": "737 752 877",
    "email": "",
    "datum_narozeni": "",
    "spravce": "",
    "budka_cislo": 58,
    "budka_nazev": ""
  },
  "059159": {
    "jmeno": "Jana",
    "osloveni": "Jani",
    "prijmeni": "DÍTĚTOVÁ",
    "telefon": "605 100 159",
    "email": "j.ditetova@vhos.cz",
    "datum_narozeni": "1959-01-30",
    "spravce": "Jana",
    "budka_cislo": 59,
    "budka_nazev": ""
  },
  "060986": {
    "jmeno": "Martin",
    "osloveni": "Martine",
    "prijmeni": "ŠOTOLA Plznička",
    "telefon": "732 520 986",
    "email": "",
    "datum_narozeni": "",
    "spravce": "Natálka",
    "budka_cislo": 60,
    "budka_nazev": "Natálka"
  },
  "061111": {
    "jmeno": "Erwin",
    "osloveni": "Erwin",
    "prijmeni": "SUKKEL",
    "telefon": "624 526 111",
    "email": "",
    "datum_narozeni": "",
    "spravce": "Erwin",
    "budka_cislo": 61,
    "budka_nazev": "Erwin Thuis"
  },
  "062109": {
    "jmeno": "Jiří",
    "osloveni": "Jirko",
    "prijmeni": "ABRAHAM",
    "telefon": "720 600 109",
    "email": "novohradka@volny.cz",
    "datum_narozeni": "1962-05-07",
    "spravce": "Erwin",
    "budka_cislo": 62,
    "budka_nazev": "Erwin Werkplaats"
  },
  "063086": {
    "jmeno": "Jirka",
    "osloveni": "Jirko",
    "prijmeni": "HAVLÍK ml.",
    "telefon": "776 141 086",
    "email": "blaukom@seznam.cz",
    "datum_narozeni": "1977-04-26",
    "spravce": "Jirka",
    "budka_cislo": 63,
    "budka_nazev": "Adla"
  },
  "064317": {
    "jmeno": "Tomáš",
    "osloveni": "Tome",
    "prijmeni": "MULLER",
    "telefon": "774 940 317",
    "email": "",
    "datum_narozeni": "",
    "spravce": "Tom",
    "budka_cislo": 64,
    "budka_nazev": "Žabka"
  },
  "065111": {
    "jmeno": "Erwin",
    "osloveni": "Erwin",
    "prijmeni": "SUKKEL",
    "telefon": "624 526 111",
    "email": "",
    "datum_narozeni": "",
    "spravce": "Erwin",
    "budka_cislo": 65,
    "budka_nazev": "Ërwin 3"
  },
  "066966": {
    "jmeno": "Milan",
    "osloveni": "Milane",
    "prijmeni": "HÁNA",
    "telefon": "733 121 966",
    "email": "starosta@rychnovnm.cz",
    "datum_narozeni": "1979-02-06",
    "spravce": "Milan st.",
    "budka_cislo": 66,
    "budka_nazev": ""
  },
  "067038": {
    "jmeno": "Dušan",
    "osloveni": "Dušane",
    "prijmeni": "NÁDASKÝ",
    "telefon": "907 780 038",
    "email": "",
    "datum_narozeni": "",
    "spravce": "Dušan",
    "budka_cislo": 67,
    "budka_nazev": "Plastika"
  },
  "068472": {
    "jmeno": "Milan",
    "osloveni": "Milane",
    "prijmeni": "KOTOULEK",
    "telefon": "602 518 472",
    "email": "",
    "datum_narozeni": "",
    "spravce": "Milan",
    "budka_cislo": 68,
    "budka_nazev": "Hanička"
  },
  "069923": {
    "jmeno": "Hana",
    "osloveni": "Hani",
    "prijmeni": "ŠLECHTOVÁ",
    "telefon": "732 671 923",
    "email": "slechtovahana@seznam.cz",
    "datum_narozeni": "",
    "spravce": "Hana",
    "budka_cislo": 69,
    "budka_nazev": "Srubec"
  },
  "070123": {
    "jmeno": "",
    "osloveni": "",
    "prijmeni": "NAVRÁTIL",
    "telefon": "605 736 123",
    "email": "",
    "datum_narozeni": "",
    "spravce": "",
    "budka_cislo": 70,
    "budka_nazev": ""
  },
  "071775": {
    "jmeno": "Martin",
    "osloveni": "Martine",
    "prijmeni": "VŠETIČKA",
    "telefon": "724 213 775",
    "email": "martin.vseticka@melzer.cz",
    "datum_narozeni": "",
    "spravce": "",
    "budka_cislo": 71,
    "budka_nazev": "Martin"
  },
  "072660": {
    "jmeno": "Michal",
    "osloveni": "Michale",
    "prijmeni": "KNÁPEK",
    "telefon": "604 653 660",
    "email": "",
    "datum_narozeni": "",
    "spravce": "",
    "budka_cislo": 72,
    "budka_nazev": "Michal"
  },
  "073154": {
    "jmeno": "Vlastimil",
    "osloveni": "Šéfe",
    "prijmeni": "ANTOŠOVSKÝ",
    "telefon": "603 375 154",
    "email": "antosovsky@seznam.cz",
    "datum_narozeni": "",
    "spravce": "Vlastik Ant.",
    "budka_cislo": 73,
    "budka_nazev": ""
  },
  "074488": {
    "jmeno": "Jirka",
    "osloveni": "Jirka",
    "prijmeni": "HAVLÍK st.",
    "telefon": "731 589 488",
    "email": "",
    "datum_narozeni": "1952-12-12",
    "spravce": "Eva",
    "budka_cislo": 74,
    "budka_nazev": ""
  },
  "075504": {
    "jmeno": "Martin",
    "osloveni": "Martine",
    "prijmeni": "NOVOTNÝ 🦉",
    "telefon": "777 676 504",
    "email": "",
    "datum_narozeni": "",
    "spravce": "Rychnov",
    "budka_cislo": 75,
    "budka_nazev": ""
  },
  "076918": {
    "jmeno": "Jiří",
    "osloveni": "Jirko",
    "prijmeni": "BACHMANN",
    "telefon": "603 818 918",
    "email": "bachmann@centrum.cz",
    "datum_narozeni": "1958-11-08",
    "spravce": "Bachman",
    "budka_cislo": 76,
    "budka_nazev": "Zdena"
  },
  "077383": {
    "jmeno": "Pavel",
    "osloveni": "Pavle",
    "prijmeni": "KISS",
    "telefon": "724 278 383",
    "email": "kiss0@centrum.cz",
    "datum_narozeni": "",
    "spravce": "Kiss",
    "budka_cislo": 77,
    "budka_nazev": "Žofka"
  },
  "078491": {
    "jmeno": "Lukáš",
    "osloveni": "Luky",
    "prijmeni": "VYKYDAL",
    "telefon": "602 356 491",
    "email": "vykydal00@gmail.com",
    "datum_narozeni": "1983-12-29",
    "spravce": "Lukáš V.",
    "budka_cislo": 78,
    "budka_nazev": "Thea - Přemky"
  },
  "079504": {
    "jmeno": "Martin",
    "osloveni": "Martine",
    "prijmeni": "NOVOTNÝ 🦉",
    "telefon": "777 676 504",
    "email": "",
    "datum_narozeni": "1972-03-16",
    "spravce": "Rychnov",
    "budka_cislo": 79,
    "budka_nazev": ""
  },
  "080491": {
    "jmeno": "Lukáš",
    "osloveni": "Luky",
    "prijmeni": "VYKYDAL",
    "telefon": "602 356 491",
    "email": "vykydal00@gmail.com",
    "datum_narozeni": "1983-12-29",
    "spravce": "Lukáš V.",
    "budka_cislo": 80,
    "budka_nazev": "Thea - Rozstání"
  },
  "081442": {
    "jmeno": "Pavel",
    "osloveni": "Pavle",
    "prijmeni": "VYROUBAL ml.",
    "telefon": "731 528 442",
    "email": "pajsek@seznam.cz",
    "datum_narozeni": "",
    "spravce": "Pajsek",
    "budka_cislo": 81,
    "budka_nazev": ""
  },
  "082179": {
    "jmeno": "Vlaďka",
    "osloveni": "Vlaďko",
    "prijmeni": "JANÍKOVÁ",
    "telefon": "721 223 179",
    "email": "janikovavladimira@seznam.cz",
    "datum_narozeni": "",
    "spravce": "Fojťas",
    "budka_cislo": 82,
    "budka_nazev": "Chille"
  },
  "083676": {
    "jmeno": "Alena",
    "osloveni": "Alčo",
    "prijmeni": "ŠIRŮČKOVÁ",
    "telefon": "721 082 676",
    "email": "",
    "datum_narozeni": "1961-10-22",
    "spravce": "Pavel",
    "budka_cislo": 83,
    "budka_nazev": "Jasmínka"
  },
  "084730": {
    "jmeno": "Tomáš",
    "osloveni": "Tome",
    "prijmeni": "ZVEJŠKA",
    "telefon": "604 942 730",
    "email": "zvejska.tom@gmail.com",
    "datum_narozeni": "1991-01-04",
    "spravce": "Tom",
    "budka_cislo": 84,
    "budka_nazev": ""
  },
  "000085": {
    "jmeno": "",
    "osloveni": "",
    "prijmeni": "",
    "telefon": "",
    "email": "",
    "datum_narozeni": "",
    "spravce": "Pavel",
    "budka_cislo": 85,
    "budka_nazev": ""
  },
  "086898": {
    "jmeno": "Roman",
    "osloveni": "Romane",
    "prijmeni": "DOBEŠ",
    "telefon": "724 005 898",
    "email": "",
    "datum_narozeni": "",
    "spravce": "Roman",
    "budka_cislo": 86,
    "budka_nazev": "Mirka"
  },
  "087578": {
    "jmeno": "Václav",
    "osloveni": "Vašku",
    "prijmeni": "STUCHLÝ",
    "telefon": "602 403 578",
    "email": "",
    "datum_narozeni": "1970-09-10",
    "spravce": "Vašek",
    "budka_cislo": 87,
    "budka_nazev": ""
  },
  "088255": {
    "jmeno": "Lucie",
    "osloveni": "Lucko",
    "prijmeni": "BÁLKOVÁ",
    "telefon": "720 274 255",
    "email": "",
    "datum_narozeni": "",
    "spravce": "Lucka",
    "budka_cislo": 88,
    "budka_nazev": "Bálkovi"
  },
  "089856": {
    "jmeno": "RAFAN",
    "osloveni": "Jardo",
    "prijmeni": "RAFAN",
    "telefon": "702 287 856",
    "email": "jnovotny45@seznam.cz",
    "datum_narozeni": "1945-05-05",
    "spravce": "Jarin",
    "budka_cislo": 89,
    "budka_nazev": ""
  },
  "000090": {
    "jmeno": "Dalibor",
    "osloveni": "Bore",
    "prijmeni": "ŠEBEK",
    "telefon": "",
    "email": "",
    "datum_narozeni": "",
    "spravce": "Dalibor",
    "budka_cislo": 90,
    "budka_nazev": ""
  },
  "091006": {
    "jmeno": "Marcela",
    "osloveni": "Macku",
    "prijmeni": "PAŘILOVÁ",
    "telefon": "775 270 006",
    "email": "",
    "datum_narozeni": "1967-12-08",
    "spravce": "Marcela Pař.",
    "budka_cislo": 91,
    "budka_nazev": ""
  },
  "092504": {
    "jmeno": "Martin",
    "osloveni": "Martine",
    "prijmeni": "NOVOTNÝ 🦉",
    "telefon": "777 676 504",
    "email": "",
    "datum_narozeni": "1972-03-16",
    "spravce": "Martin Nov",
    "budka_cislo": 92,
    "budka_nazev": ""
  },
  "093799": {
    "jmeno": "Michaela",
    "osloveni": "Míšo",
    "prijmeni": "SMEJKALOVÁ",
    "telefon": "777 079 799",
    "email": "",
    "datum_narozeni": "",
    "spravce": "Martin Nov",
    "budka_cislo": 93,
    "budka_nazev": ""
  },
  "094504": {
    "jmeno": "Martin",
    "osloveni": "Martine",
    "prijmeni": "NOVOTNÝ 🦉",
    "telefon": "777 676 504",
    "email": "",
    "datum_narozeni": "1972-03-16",
    "spravce": "Martin Nov",
    "budka_cislo": 94,
    "budka_nazev": ""
  },
  "095799": {
    "jmeno": "Michaela",
    "osloveni": "Míšo",
    "prijmeni": "SMEJKALOVÁ",
    "telefon": "777 079 799",
    "email": "",
    "datum_narozeni": "",
    "spravce": "Martin Nov",
    "budka_cislo": 95,
    "budka_nazev": ""
  },
  "096641": {
    "jmeno": "Martina",
    "osloveni": "Martino",
    "prijmeni": "PAULUSOVÁ",
    "telefon": "728 177 641",
    "email": "",
    "datum_narozeni": "",
    "spravce": "Milan H.",
    "budka_cislo": 96,
    "budka_nazev": ""
  },
  "097641": {
    "jmeno": "Martina",
    "osloveni": "Martino",
    "prijmeni": "PAULUSOVÁ",
    "telefon": "728 177 641",
    "email": "",
    "datum_narozeni": "",
    "spravce": "Martina",
    "budka_cislo": 97,
    "budka_nazev": ""
  },
  "098591": {
    "jmeno": "Iva",
    "osloveni": "Ivo",
    "prijmeni": "OPTIČKA",
    "telefon": "603 589 591",
    "email": "",
    "datum_narozeni": "",
    "spravce": "Štěpánková",
    "budka_cislo": 98,
    "budka_nazev": ""
  },
  "099641": {
    "jmeno": "Martina",
    "osloveni": "Martino",
    "prijmeni": "PAULUSOVÁ",
    "telefon": "728 177 641",
    "email": "",
    "datum_narozeni": "",
    "spravce": "Milan H.",
    "budka_cislo": 99,
    "budka_nazev": ""
  },
  "100977": {
    "jmeno": "Ema",
    "osloveni": "Emo",
    "prijmeni": "EMUŠKA",
    "telefon": "607 135 977",
    "email": "",
    "datum_narozeni": "1965-07-24",
    "spravce": "Ema",
    "budka_cislo": 100,
    "budka_nazev": "Ema-Emuška"
  },
  "101826": {
    "jmeno": "Lukáš",
    "osloveni": "Luky",
    "prijmeni": "SASÍN",
    "telefon": "606 619 826",
    "email": "lukas.sasin@zemsky.cz",
    "datum_narozeni": "",
    "spravce": "Lukáš Sasin",
    "budka_cislo": 101,
    "budka_nazev": ""
  },
  "000102": {
    "jmeno": "",
    "osloveni": "",
    "prijmeni": "",
    "telefon": "",
    "email": "",
    "datum_narozeni": "",
    "spravce": "obec",
    "budka_cislo": 102,
    "budka_nazev": ""
  },
  "000103": {
    "jmeno": "",
    "osloveni": "",
    "prijmeni": "",
    "telefon": "",
    "email": "",
    "datum_narozeni": "",
    "spravce": "obec",
    "budka_cislo": 103,
    "budka_nazev": ""
  },
  "104560": {
    "jmeno": "Jana",
    "osloveni": "Jani",
    "prijmeni": "DOSEDLOVÁ",
    "telefon": "605 476 560",
    "email": "",
    "datum_narozeni": "",
    "spravce": "DPS",
    "budka_cislo": 104,
    "budka_nazev": ""
  },
  "000105": {
    "jmeno": "",
    "osloveni": "",
    "prijmeni": "",
    "telefon": "",
    "email": "",
    "datum_narozeni": "",
    "spravce": "obec",
    "budka_cislo": 105,
    "budka_nazev": ""
  },
  "000106": {
    "jmeno": "",
    "osloveni": "",
    "prijmeni": "",
    "telefon": "",
    "email": "",
    "datum_narozeni": "",
    "spravce": "obec",
    "budka_cislo": 106,
    "budka_nazev": ""
  },
  "107060": {
    "jmeno": "Josef",
    "osloveni": "Pepo",
    "prijmeni": "BIDMON",
    "telefon": "608 779 060",
    "email": "bidmon@bidmon.cz",
    "datum_narozeni": "1959-02-27",
    "spravce": "Pepa",
    "budka_cislo": 107,
    "budka_nazev": ""
  },
  "108372": {
    "jmeno": "Marek",
    "osloveni": "Marku",
    "prijmeni": "KOUTNÝ",
    "telefon": "602 581 372",
    "email": "marek.koutny@bmh.cz",
    "datum_narozeni": "",
    "spravce": "Koutný",
    "budka_cislo": 108,
    "budka_nazev": "Marek"
  },
  "109372": {
    "jmeno": "Marek",
    "osloveni": "Marku",
    "prijmeni": "KOUTNÝ",
    "telefon": "602 581 372",
    "email": "marek.koutny@bmh.cz",
    "datum_narozeni": "",
    "spravce": "Koutný",
    "budka_cislo": 109,
    "budka_nazev": "PODLAS"
  },
  "110372": {
    "jmeno": "Marek",
    "osloveni": "Marku",
    "prijmeni": "KOUTNÝ",
    "telefon": "602 581 372",
    "email": "marek.koutny@bmh.cz",
    "datum_narozeni": "",
    "spravce": "Koutný",
    "budka_cislo": 110,
    "budka_nazev": "Maty"
  },
  "111810": {
    "jmeno": "Oldřich",
    "osloveni": "Oldo",
    "prijmeni": "SYROVÁTKO",
    "telefon": "776 092 810",
    "email": "",
    "datum_narozeni": "",
    "spravce": "Olda",
    "budka_cislo": 111,
    "budka_nazev": "Vojta"
  },
  "112776": {
    "jmeno": "Jiří",
    "osloveni": "Jirko",
    "prijmeni": "FABIÁN",
    "telefon": "778 882 776",
    "email": "jirin.fabos@seznam.cz",
    "datum_narozeni": "",
    "spravce": "J. Fabián",
    "budka_cislo": 112,
    "budka_nazev": ""
  },
  "113776": {
    "jmeno": "Jiří",
    "osloveni": "Jirko",
    "prijmeni": "FABIÁN",
    "telefon": "778 882 776",
    "email": "jirin.fabos@seznam.cz",
    "datum_narozeni": "",
    "spravce": "J. Fabián",
    "budka_cislo": 113,
    "budka_nazev": ""
  },
  "000114": {
    "jmeno": "",
    "osloveni": "",
    "prijmeni": "",
    "telefon": "",
    "email": "",
    "datum_narozeni": "",
    "spravce": "Tom",
    "budka_cislo": 114,
    "budka_nazev": "Tomík"
  },
  "115714": {
    "jmeno": "PEŤA",
    "osloveni": "Peťo",
    "prijmeni": "PEŤA",
    "telefon": "777 662 714",
    "email": "info@petrkobelka.cz",
    "datum_narozeni": "1984-07-28",
    "spravce": "Kiki",
    "budka_cislo": 115,
    "budka_nazev": "Kiki"
  },
  "116109": {
    "jmeno": "Jiří",
    "osloveni": "Jirko",
    "prijmeni": "ABRAHAM",
    "telefon": "720 600 109",
    "email": "novohradka@volny.cz",
    "datum_narozeni": "1962-05-07",
    "spravce": "Jirka",
    "budka_cislo": 116,
    "budka_nazev": "Karolína"
  },
  "117109": {
    "jmeno": "Jiří",
    "osloveni": "Jirko",
    "prijmeni": "ABRAHAM",
    "telefon": "720 600 109",
    "email": "novohradka@volny.cz",
    "datum_narozeni": "1962-05-07",
    "spravce": "Jirka",
    "budka_cislo": 117,
    "budka_nazev": "Julie"
  },
  "118472": {
    "jmeno": "Milan",
    "osloveni": "Milane",
    "prijmeni": "KOTOULEK",
    "telefon": "602 518 472",
    "email": "",
    "datum_narozeni": "",
    "spravce": "Milan",
    "budka_cislo": 118,
    "budka_nazev": "Tadeáš"
  },
  "000119": {
    "jmeno": "",
    "osloveni": "",
    "prijmeni": "",
    "telefon": "",
    "email": "",
    "datum_narozeni": "",
    "spravce": "obec",
    "budka_cislo": 119,
    "budka_nazev": ""
  },
  "000120": {
    "jmeno": "",
    "osloveni": "",
    "prijmeni": "",
    "telefon": "",
    "email": "",
    "datum_narozeni": "",
    "spravce": "obec",
    "budka_cislo": 120,
    "budka_nazev": ""
  },
  "000121": {
    "jmeno": "",
    "osloveni": "",
    "prijmeni": "",
    "telefon": "",
    "email": "",
    "datum_narozeni": "",
    "spravce": "obec",
    "budka_cislo": 121,
    "budka_nazev": ""
  },
  "000122": {
    "jmeno": "",
    "osloveni": "",
    "prijmeni": "",
    "telefon": "",
    "email": "",
    "datum_narozeni": "",
    "spravce": "obec",
    "budka_cislo": 122,
    "budka_nazev": ""
  },
  "000123": {
    "jmeno": "",
    "osloveni": "",
    "prijmeni": "",
    "telefon": "",
    "email": "",
    "datum_narozeni": "",
    "spravce": "obec",
    "budka_cislo": 123,
    "budka_nazev": ""
  },
  "124998": {
    "jmeno": "Dalibor",
    "osloveni": "Bore",
    "prijmeni": "ŠEBEK",
    "telefon": "724 068 998",
    "email": "dsebek@seznam.cz",
    "datum_narozeni": "",
    "spravce": "Dalibor",
    "budka_cislo": 124,
    "budka_nazev": ""
  },
  "125023": {
    "jmeno": "Martin",
    "osloveni": "Martine",
    "prijmeni": "GÁLEK",
    "telefon": "773 785 023",
    "email": "",
    "datum_narozeni": "",
    "spravce": "Anna",
    "budka_cislo": 125,
    "budka_nazev": "Daminán"
  },
  "126843": {
    "jmeno": "Ladislav",
    "osloveni": "Laďo",
    "prijmeni": "ŠAFR",
    "telefon": "603 261 843",
    "email": "safrladislavst@gmail.com",
    "datum_narozeni": "1954-04-25",
    "spravce": "Laďa",
    "budka_cislo": 126,
    "budka_nazev": ""
  },
  "127736": {
    "jmeno": "Alice",
    "osloveni": "Alice",
    "prijmeni": "ŠKVRNOVÁ",
    "telefon": "605 739 736",
    "email": "",
    "datum_narozeni": "",
    "spravce": "Alice",
    "budka_cislo": 127,
    "budka_nazev": "Olda+Martin"
  },
  "128376": {
    "jmeno": "Zdeněk",
    "osloveni": "Zdenku",
    "prijmeni": "JANOUŠEK",
    "telefon": "604 550 376",
    "email": "",
    "datum_narozeni": "",
    "spravce": "vinař",
    "budka_cislo": 128,
    "budka_nazev": ""
  },
  "129863": {
    "jmeno": "Vašek",
    "osloveni": "Vašku",
    "prijmeni": "SLECHAN",
    "telefon": "608 141 863",
    "email": "obec.brezina@post.cz",
    "datum_narozeni": "",
    "spravce": "Vašek",
    "budka_cislo": 129,
    "budka_nazev": ""
  },
  "130846": {
    "jmeno": "Jakub",
    "osloveni": "Kubo",
    "prijmeni": "MARTÍNEK",
    "telefon": "727 870 846",
    "email": "",
    "datum_narozeni": "",
    "spravce": "Pavel",
    "budka_cislo": 130,
    "budka_nazev": ""
  },
  "131731": {
    "jmeno": "Miroslava",
    "osloveni": "Mirko",
    "prijmeni": "ČEPOVÁ",
    "telefon": "703 145 731",
    "email": "psjevicko@seznam.cz",
    "datum_narozeni": "1982-05-31",
    "spravce": "Jana",
    "budka_cislo": 131,
    "budka_nazev": "babi Draha"
  },
  "132882": {
    "jmeno": "Jiří",
    "osloveni": "Jirko",
    "prijmeni": "BERKA",
    "telefon": "604 298 882",
    "email": "jiri.berka@daldrop.cz",
    "datum_narozeni": "",
    "spravce": "Jirka",
    "budka_cislo": 132,
    "budka_nazev": ""
  },
  "133982": {
    "jmeno": "Petr",
    "osloveni": "Oskare",
    "prijmeni": "SOUKUP",
    "telefon": "608 536 982",
    "email": "oberwinkl@seznam.cz",
    "datum_narozeni": "",
    "spravce": "Peťa",
    "budka_cislo": 133,
    "budka_nazev": "Oskar"
  },
  "134199": {
    "jmeno": "Milan",
    "osloveni": "Milane",
    "prijmeni": "HORŇÁK",
    "telefon": "724 180 199",
    "email": "",
    "datum_narozeni": "",
    "spravce": "Milan",
    "budka_cislo": 134,
    "budka_nazev": "Hvězdička"
  },
  "135164": {
    "jmeno": "Radek",
    "osloveni": "Radku",
    "prijmeni": "PTÁK",
    "telefon": "731 084 164",
    "email": "radoslavptak@gmail.com",
    "datum_narozeni": "",
    "spravce": "Radek",
    "budka_cislo": 135,
    "budka_nazev": ""
  },
  "136754": {
    "jmeno": "Hana",
    "osloveni": "Hani",
    "prijmeni": "VYKYDALOVÁ",
    "telefon": "601 128 754",
    "email": "",
    "datum_narozeni": "",
    "spravce": "Luky",
    "budka_cislo": 136,
    "budka_nazev": "Chateau Lačnov"
  },
  "137044": {
    "jmeno": "Radko",
    "osloveni": "Radku",
    "prijmeni": "MARTÍNEK",
    "telefon": "724 652 044",
    "email": "",
    "datum_narozeni": "",
    "spravce": "Radko",
    "budka_cislo": 137,
    "budka_nazev": ""
  },
  "138120": {
    "jmeno": "Václav",
    "osloveni": "Vašku",
    "prijmeni": "DVOŘÁK",
    "telefon": "603 101 120",
    "email": "obec.krenov@seznam.cz",
    "datum_narozeni": "1970-04-18",
    "spravce": "Vašek",
    "budka_cislo": 138,
    "budka_nazev": "U starosty"
  },
  "139451": {
    "jmeno": "Stanislav",
    "osloveni": "Staňo",
    "prijmeni": "KAMENICKÝ",
    "telefon": "731 500 451",
    "email": "stanislav.kamenicky@gmail.com",
    "datum_narozeni": "1962-03-20",
    "spravce": "Staňa",
    "budka_cislo": 139,
    "budka_nazev": "Honzík"
  },
  "140161": {
    "jmeno": "Petr",
    "osloveni": "Peťo",
    "prijmeni": "KOUTNÝ",
    "telefon": "739 117 161",
    "email": "",
    "datum_narozeni": "",
    "spravce": "Petr",
    "budka_cislo": 140,
    "budka_nazev": "Adélka+Petr"
  },
  "000141": {
    "jmeno": "",
    "osloveni": "",
    "prijmeni": "",
    "telefon": "",
    "email": "",
    "datum_narozeni": "",
    "spravce": "",
    "budka_cislo": 141,
    "budka_nazev": "STAVOKA"
  },
  "142714": {
    "jmeno": "PEŤA",
    "osloveni": "Peťo",
    "prijmeni": "PEŤA",
    "telefon": "777 662 714",
    "email": "info@petrkobelka.gmail",
    "datum_narozeni": "1984-07-28",
    "spravce": "Péťa DEM",
    "budka_cislo": 142,
    "budka_nazev": "Péťa"
  },
  "143118": {
    "jmeno": "Libor",
    "osloveni": "Libore",
    "prijmeni": "CACH",
    "telefon": "604 648 118",
    "email": "starosta@obecdlouhaloucka.cz",
    "datum_narozeni": "1967-07-10",
    "spravce": "Libor",
    "budka_cislo": 143,
    "budka_nazev": "Adélka"
  },
  "144271": {
    "jmeno": "Milan",
    "osloveni": "?",
    "prijmeni": "MÍKA",
    "telefon": "602 833 271",
    "email": "mmika.vak@gmail.com",
    "datum_narozeni": "",
    "spravce": "Ríša",
    "budka_cislo": 144,
    "budka_nazev": "Markéta"
  },
  "145990": {
    "jmeno": "Vlasta",
    "osloveni": "Milane",
    "prijmeni": "NA VRŠÍCH",
    "telefon": "774 504 990",
    "email": "",
    "datum_narozeni": "",
    "spravce": "Vlasta",
    "budka_cislo": 145,
    "budka_nazev": "Na vrších"
  },
  "146648": {
    "jmeno": "Roland",
    "osloveni": "Rolo",
    "prijmeni": "KOSCHATA",
    "telefon": "604 143 648",
    "email": "",
    "datum_narozeni": "",
    "spravce": "Rolo",
    "budka_cislo": 146,
    "budka_nazev": "Drahuška"
  },
  "147563": {
    "jmeno": "Zuzana",
    "osloveni": "Zuzko",
    "prijmeni": "KALINČíKOVÁ",
    "telefon": "915 996 563",
    "email": "zuzana.kalincikova@xylem.com",
    "datum_narozeni": "",
    "spravce": "Zuzka",
    "budka_cislo": 147,
    "budka_nazev": ""
  },
  "148470": {
    "jmeno": "Lukáš",
    "osloveni": "Luky",
    "prijmeni": "MAREŠ",
    "telefon": "775 575 470",
    "email": "mares@jezerka.cz",
    "datum_narozeni": "",
    "spravce": "Lukáš",
    "budka_cislo": 148,
    "budka_nazev": ""
  },
  "149513": {
    "jmeno": "Markéta",
    "osloveni": "Markéto",
    "prijmeni": "PAULOVÁ",
    "telefon": "607 220 513",
    "email": "",
    "datum_narozeni": "",
    "spravce": "Markéta",
    "budka_cislo": 149,
    "budka_nazev": "Markéta"
  },
  "150837": {
    "jmeno": "Jiří",
    "osloveni": "Jirko",
    "prijmeni": "PAUL",
    "telefon": "602 674 837",
    "email": "jiri.paul@vakberoun.cz",
    "datum_narozeni": "1972-03-19",
    "spravce": "Jirka",
    "budka_cislo": 150,
    "budka_nazev": "Jindřichovka"
  },
  "151260": {
    "jmeno": "Ivan",
    "osloveni": "Ivane",
    "prijmeni": "KAFKA",
    "telefon": "725 505 260",
    "email": "ivan.kafka@energieag.cz",
    "datum_narozeni": "1975-12-15",
    "spravce": "Ivan",
    "budka_cislo": 151,
    "budka_nazev": "Ivan"
  },
  "152825": {
    "jmeno": "Sylva",
    "osloveni": "Sylvo",
    "prijmeni": "ŘEZNÍČKOVÁ",
    "telefon": "603 899 825",
    "email": "",
    "datum_narozeni": "",
    "spravce": "Sylva",
    "budka_cislo": 152,
    "budka_nazev": ""
  },
  "153333": {
    "jmeno": "Pavel",
    "osloveni": "Pavle",
    "prijmeni": "SEJKORA",
    "telefon": "605 804 333",
    "email": "trinitas@unet.cz",
    "datum_narozeni": "",
    "spravce": "Pavel",
    "budka_cislo": 153,
    "budka_nazev": ""
  },
  "154791": {
    "jmeno": "Petr",
    "osloveni": "Peťo",
    "prijmeni": "VEDRA",
    "telefon": "724 918 791",
    "email": "petr.vedra@vak-km.cz",
    "datum_narozeni": "",
    "spravce": "Peťa",
    "budka_cislo": 154,
    "budka_nazev": "Všetulka"
  },
  "155831": {
    "jmeno": "Michal",
    "osloveni": "Michale",
    "prijmeni": "KOLEŠ",
    "telefon": "603 541 831",
    "email": "michal.koles@gmail.com",
    "datum_narozeni": "",
    "spravce": "Michal",
    "budka_cislo": 155,
    "budka_nazev": ""
  },
  "156840": {
    "jmeno": "Milan",
    "osloveni": "Milane",
    "prijmeni": "DRDA",
    "telefon": "737 240 840",
    "email": "drda@envi-pur.cz",
    "datum_narozeni": "",
    "spravce": "Milan",
    "budka_cislo": 156,
    "budka_nazev": "U Rebeky a Oskara"
  },
  "157055": {
    "jmeno": "Aleš",
    "osloveni": "Aleši",
    "prijmeni": "KRKOŠKA",
    "telefon": "724 643 055",
    "email": "ales.krkoska@hutira.cz",
    "datum_narozeni": "",
    "spravce": "Aleš",
    "budka_cislo": 157,
    "budka_nazev": "HUTIRA"
  },
  "158417": {
    "jmeno": "Roman",
    "osloveni": "Romane",
    "prijmeni": "PEŠEK-G",
    "telefon": "739 521 417",
    "email": "roman.pesek@gasco.cz",
    "datum_narozeni": "",
    "spravce": "Roman",
    "budka_cislo": 158,
    "budka_nazev": "Jíťa"
  },
  "159325": {
    "jmeno": "Veronika",
    "osloveni": "Verčo",
    "prijmeni": "CAISOVÁ",
    "telefon": "775 054 325",
    "email": "",
    "datum_narozeni": "",
    "spravce": "Veronika",
    "budka_cislo": 159,
    "budka_nazev": "Kubovka 63"
  },
  "160953": {
    "jmeno": "Roman",
    "osloveni": "Romane",
    "prijmeni": "BADIN",
    "telefon": "606 666 953",
    "email": "roman.badin@vakberoun.cz",
    "datum_narozeni": "",
    "spravce": "Roman",
    "budka_cislo": 160,
    "budka_nazev": ""
  },
  "161271": {
    "jmeno": "Milan",
    "osloveni": "Milane",
    "prijmeni": "MÍKA",
    "telefon": "602833271",
    "email": "mmika.vak@gmail.com",
    "datum_narozeni": "",
    "spravce": "Milan",
    "budka_cislo": 161,
    "budka_nazev": ""
  },
  "162342": {
    "jmeno": "David",
    "osloveni": "Davide",
    "prijmeni": "ROHÁČEK",
    "telefon": "778 046 342",
    "email": "david.rohacek@vhos.cz",
    "datum_narozeni": "1997-01-06",
    "spravce": "Michal",
    "budka_cislo": 162,
    "budka_nazev": ""
  },
  "163714": {
    "jmeno": "František",
    "osloveni": "Franto",
    "prijmeni": "",
    "telefon": "728419714",
    "email": "",
    "datum_narozeni": "",
    "spravce": "František",
    "budka_cislo": 163,
    "budka_nazev": ""
  },
  "164253": {
    "jmeno": "Marie",
    "osloveni": "Maruško",
    "prijmeni": "ZEMÁNKOVÁ",
    "telefon": "775 299 253",
    "email": "zemankovar@seznam.cz",
    "datum_narozeni": "",
    "spravce": "Marie",
    "budka_cislo": 164,
    "budka_nazev": ""
  },
  "165399": {
    "jmeno": "Karel",
    "osloveni": "Karle",
    "prijmeni": "ŽÁČEK",
    "telefon": "727 931 399",
    "email": "karel.zacek@kapka-vodomery.cz",
    "datum_narozeni": "1986-04-09",
    "spravce": "Karel",
    "budka_cislo": 165,
    "budka_nazev": "Kapka"
  },
  "166260": {
    "jmeno": "Ivan",
    "osloveni": "Ivane",
    "prijmeni": "KAFKA",
    "telefon": "725 505 260",
    "email": "ivan.kafka@energieag.cz",
    "datum_narozeni": "1975-12-15",
    "spravce": "Ivan",
    "budka_cislo": 166,
    "budka_nazev": ""
  },
  "167500": {
    "jmeno": "Miroslav",
    "osloveni": "Mirku",
    "prijmeni": "RYS",
    "telefon": "725785500",
    "email": "",
    "datum_narozeni": "",
    "spravce": "Mirek",
    "budka_cislo": 167,
    "budka_nazev": ""
  },
  "168456": {
    "jmeno": "Jakub",
    "osloveni": "Kubo",
    "prijmeni": "JANOUŠEK",
    "telefon": "777 004 456",
    "email": "",
    "datum_narozeni": "",
    "spravce": "",
    "budka_cislo": 168,
    "budka_nazev": "Tondova budka"
  },
  "169377": {
    "jmeno": "Miroslav",
    "osloveni": "Mirku",
    "prijmeni": "BERAN",
    "telefon": "905 188 377",
    "email": "packetalc@gmail.com",
    "datum_narozeni": "",
    "spravce": "Miro",
    "budka_cislo": 169,
    "budka_nazev": ""
  },
  "170953": {
    "jmeno": "Roman",
    "osloveni": "Romane",
    "prijmeni": "BADIN",
    "telefon": "606 666 953",
    "email": "roman.badin@vakberoun.cz",
    "datum_narozeni": "",
    "spravce": "Roman",
    "budka_cislo": 170,
    "budka_nazev": ""
  },
  "171673": {
    "jmeno": "Miloš",
    "osloveni": "Miloši",
    "prijmeni": "ALTMAN",
    "telefon": "722 460 673",
    "email": "altmann-milos@email.cz",
    "datum_narozeni": "",
    "spravce": "Miloš",
    "budka_cislo": 171,
    "budka_nazev": ""
  },
  "172842": {
    "jmeno": "Vladimír",
    "osloveni": "Vláďo",
    "prijmeni": "KŘIVONOSKA",
    "telefon": "608 713 842",
    "email": "",
    "datum_narozeni": "",
    "spravce": "Vláďa",
    "budka_cislo": 172,
    "budka_nazev": ""
  },
  "173444": {
    "jmeno": "Marcela",
    "osloveni": "Marcelo",
    "prijmeni": "DVOŘÁKOVÁ",
    "telefon": "608 853 444",
    "email": "",
    "datum_narozeni": "",
    "spravce": "Marcela",
    "budka_cislo": 173,
    "budka_nazev": "Kolombo šel na sever"
  },
  "174087": {
    "jmeno": "Ludmila",
    "osloveni": "Lído",
    "prijmeni": "STANIKOVÁ",
    "telefon": "739 413 087",
    "email": "stanikova.lidu@seznam.cz",
    "datum_narozeni": "",
    "spravce": "Víťa",
    "budka_cislo": 174,
    "budka_nazev": ""
  },
  "175523": {
    "jmeno": "Víťa",
    "osloveni": "Víťo",
    "prijmeni": "ABRAHÁM",
    "telefon": "606 322 523",
    "email": "",
    "datum_narozeni": "",
    "spravce": "",
    "budka_cislo": 175,
    "budka_nazev": "Víťa"
  },
  "176834": {
    "jmeno": "Dušan",
    "osloveni": "Dušane",
    "prijmeni": "TÉR",
    "telefon": "606 616 834",
    "email": "ter@vakna.cz",
    "datum_narozeni": "",
    "spravce": "",
    "budka_cislo": 176,
    "budka_nazev": ""
  },
  "177339": {
    "jmeno": "Gábi",
    "osloveni": "Gábi",
    "prijmeni": "",
    "telefon": "777 788 339",
    "email": "",
    "datum_narozeni": "",
    "spravce": "Gábi",
    "budka_cislo": 177,
    "budka_nazev": "Gábi"
  },
  "178517": {
    "jmeno": "Vladimír",
    "osloveni": "Vláďo",
    "prijmeni": "BUREŠ",
    "telefon": "725 341 517",
    "email": "metali@metali.cz",
    "datum_narozeni": "",
    "spravce": "Vladimír",
    "budka_cislo": 178,
    "budka_nazev": "Marie"
  },
  "000179": {
    "jmeno": "",
    "osloveni": "",
    "prijmeni": "",
    "telefon": "",
    "email": "",
    "datum_narozeni": "",
    "spravce": "Ota",
    "budka_cislo": 179,
    "budka_nazev": ""
  },
  "180646": {
    "jmeno": "Michal",
    "osloveni": "Michale",
    "prijmeni": "KUNC",
    "telefon": "602449646",
    "email": "",
    "datum_narozeni": "",
    "spravce": "Michal",
    "budka_cislo": 180,
    "budka_nazev": "Ptáčenka"
  },
  "000181": {
    "jmeno": "",
    "osloveni": "",
    "prijmeni": "",
    "telefon": "",
    "email": "",
    "datum_narozeni": "",
    "spravce": "Martin",
    "budka_cislo": 181,
    "budka_nazev": "Na Smuteční vrbě"
  },
  "182055": {
    "jmeno": "Katka",
    "osloveni": "Katklo",
    "prijmeni": "ČERNÁ",
    "telefon": "723 532 055",
    "email": "",
    "datum_narozeni": "",
    "spravce": "Katka",
    "budka_cislo": 182,
    "budka_nazev": "Libuška"
  },
  "183457": {
    "jmeno": "Jan",
    "osloveni": "Honzo",
    "prijmeni": "KUBAŇ",
    "telefon": "724939457",
    "email": "",
    "datum_narozeni": "",
    "spravce": "Honza",
    "budka_cislo": 183,
    "budka_nazev": ""
  },
  "184002": {
    "jmeno": "Marie",
    "osloveni": "Mařenko",
    "prijmeni": "BYRTUSOVÁ",
    "telefon": "736 609 002",
    "email": "",
    "datum_narozeni": "",
    "spravce": "Marie",
    "budka_cislo": 184,
    "budka_nazev": "Maruška"
  },
  "185629": {
    "jmeno": "Jan",
    "osloveni": "Honzo",
    "prijmeni": "KŘÍŽ",
    "telefon": "774 041 629",
    "email": "",
    "datum_narozeni": "",
    "spravce": "Honza",
    "budka_cislo": 185,
    "budka_nazev": "Kostelec"
  },
  "000186": {
    "jmeno": "Martin",
    "osloveni": "Martine",
    "prijmeni": "NOVOTNÝ 🦉",
    "telefon": "777 676 504",
    "email": "",
    "datum_narozeni": "1972-03-16",
    "spravce": "Martin",
    "budka_cislo": 186,
    "budka_nazev": "Na Lípě"
  },
  "000187": {
    "jmeno": "",
    "osloveni": "",
    "prijmeni": "",
    "telefon": "",
    "email": "",
    "datum_narozeni": "",
    "spravce": "",
    "budka_cislo": 187,
    "budka_nazev": ""
  },
  "000188": {
    "jmeno": "",
    "osloveni": "",
    "prijmeni": "",
    "telefon": "",
    "email": "",
    "datum_narozeni": "",
    "spravce": "",
    "budka_cislo": 188,
    "budka_nazev": ""
  },
  "189598": {
    "jmeno": "Vlastimil",
    "osloveni": "Vlasťo",
    "prijmeni": "DVOŘÁK",
    "telefon": "724 315 598",
    "email": "vlastimil.dvorak@sensus-int.com",
    "datum_narozeni": "",
    "spravce": "Vlasta",
    "budka_cislo": 189,
    "budka_nazev": "Dvořibudka"
  },
  "190554": {
    "jmeno": "Jan",
    "osloveni": "Honzo",
    "prijmeni": "GROSSHOF",
    "telefon": "777 333 554",
    "email": "",
    "datum_narozeni": "",
    "spravce": "Honza",
    "budka_cislo": 190,
    "budka_nazev": "Birdie"
  },
  "191351": {
    "jmeno": "Eva",
    "osloveni": "Evi",
    "prijmeni": "ĎABOLKOVÁ",
    "telefon": "602 108 351",
    "email": "e.dabolkova@avkvodka.cz",
    "datum_narozeni": "",
    "spravce": "Eva",
    "budka_cislo": 191,
    "budka_nazev": "Ptačí domeček na Salisově"
  },
  "192450": {
    "jmeno": "Miloš",
    "osloveni": "Miloši",
    "prijmeni": "VÁCLAVEK",
    "telefon": "727 977 450",
    "email": "",
    "datum_narozeni": "1954-12-28",
    "spravce": "Miloš",
    "budka_cislo": 192,
    "budka_nazev": "DOMITA"
  },
  "193471": {
    "jmeno": "Jan",
    "osloveni": "Honzo",
    "prijmeni": "RADA",
    "telefon": "602 356 471",
    "email": "jan.rada.009@gmail.com",
    "datum_narozeni": "1979-01-09",
    "spravce": "Lucie",
    "budka_cislo": 193,
    "budka_nazev": "Lucie"
  },
  "194612": {
    "jmeno": "Martin",
    "osloveni": "Martine",
    "prijmeni": "ZAHÁLKA",
    "telefon": "737271612",
    "email": "",
    "datum_narozeni": "",
    "spravce": "Martin",
    "budka_cislo": 194,
    "budka_nazev": ""
  },
  "195785": {
    "jmeno": "Jiří",
    "osloveni": "Jirko",
    "prijmeni": "WOLF",
    "telefon": "732 712 785",
    "email": "obec@brezinky.cz",
    "datum_narozeni": "",
    "spravce": "Jirka",
    "budka_cislo": 195,
    "budka_nazev": "Kryštůfek"
  },
  "196963": {
    "jmeno": "Simona",
    "osloveni": "Simono",
    "prijmeni": "SVIATIKOVÁ",
    "telefon": "908 466 963",
    "email": "sima.svatikova@gmail.com",
    "datum_narozeni": "",
    "spravce": "Simona",
    "budka_cislo": 196,
    "budka_nazev": "U Simony"
  },
  "197450": {
    "jmeno": "Tomáš",
    "osloveni": "Tome",
    "prijmeni": "KONOPIŠTĚ",
    "telefon": "605 021 450",
    "email": "",
    "datum_narozeni": "",
    "spravce": "Tomáš",
    "budka_cislo": 197,
    "budka_nazev": ""
  },
  "198825": {
    "jmeno": "Sylva",
    "osloveni": "Sylvo",
    "prijmeni": "ŘEZNÍČKOVÁ",
    "telefon": "603 899 825",
    "email": "",
    "datum_narozeni": "",
    "spravce": "",
    "budka_cislo": 198,
    "budka_nazev": ""
  },
  "199538": {
    "jmeno": "Radek",
    "osloveni": "Radku",
    "prijmeni": "NOLC",
    "telefon": "724 025 538",
    "email": "",
    "datum_narozeni": "",
    "spravce": "Radek",
    "budka_cislo": 199,
    "budka_nazev": "Zábělá 358"
  },
  "000200": {
    "jmeno": "",
    "osloveni": "",
    "prijmeni": "",
    "telefon": "",
    "email": "",
    "datum_narozeni": "",
    "spravce": "",
    "budka_cislo": 200,
    "budka_nazev": ""
  },
  "000201": {
    "jmeno": "",
    "osloveni": "",
    "prijmeni": "",
    "telefon": "",
    "email": "",
    "datum_narozeni": "",
    "spravce": "",
    "budka_cislo": 201,
    "budka_nazev": ""
  },
  "000202": {
    "jmeno": "",
    "osloveni": "",
    "prijmeni": "",
    "telefon": "",
    "email": "",
    "datum_narozeni": "",
    "spravce": "",
    "budka_cislo": 202,
    "budka_nazev": ""
  },
  "203008": {
    "jmeno": "Jarda",
    "osloveni": "Jardo",
    "prijmeni": "ČERNOŠEK",
    "telefon": "775 600 008",
    "email": "",
    "datum_narozeni": "",
    "spravce": "",
    "budka_cislo": 203,
    "budka_nazev": ""
  },
  "204940": {
    "jmeno": "Josef",
    "osloveni": "Pepo",
    "prijmeni": "KARHAN",
    "telefon": "607 185 940",
    "email": "",
    "datum_narozeni": "",
    "spravce": "Josef",
    "budka_cislo": 204,
    "budka_nazev": "Děda"
  },
  "205269": {
    "jmeno": "Pavel",
    "osloveni": "Pavle",
    "prijmeni": "FERINA",
    "telefon": "734 171 269",
    "email": "",
    "datum_narozeni": "",
    "spravce": "Pavel",
    "budka_cislo": 205,
    "budka_nazev": "Budka pro Pavla"
  },
  "206573": {
    "jmeno": "Josef",
    "osloveni": "Pepíku",
    "prijmeni": "CACÁK",
    "telefon": "602 346 573",
    "email": "",
    "datum_narozeni": "1973-01-31",
    "spravce": "",
    "budka_cislo": 206,
    "budka_nazev": ""
  },
  "207540": {
    "jmeno": "Jiří",
    "osloveni": "Jirko",
    "prijmeni": "NOVÁČEK",
    "telefon": "605208540",
    "email": "",
    "datum_narozeni": "",
    "spravce": "Jirka",
    "budka_cislo": 207,
    "budka_nazev": "Tonča"
  },
  "208540": {
    "jmeno": "Jiří",
    "osloveni": "Jirko",
    "prijmeni": "NOVÁČEK",
    "telefon": "605208540",
    "email": "",
    "datum_narozeni": "",
    "spravce": "Jirka",
    "budka_cislo": 208,
    "budka_nazev": "Manča"
  },
  "000209": {
    "jmeno": "",
    "osloveni": "",
    "prijmeni": "",
    "telefon": "",
    "email": "",
    "datum_narozeni": "",
    "spravce": "",
    "budka_cislo": 209,
    "budka_nazev": ""
  },
  "000210": {
    "jmeno": "",
    "osloveni": "",
    "prijmeni": "",
    "telefon": "",
    "email": "",
    "datum_narozeni": "",
    "spravce": "",
    "budka_cislo": 210,
    "budka_nazev": ""
  },
  "000211": {
    "jmeno": "",
    "osloveni": "",
    "prijmeni": "",
    "telefon": "",
    "email": "",
    "datum_narozeni": "",
    "spravce": "",
    "budka_cislo": 211,
    "budka_nazev": ""
  },
  "000212": {
    "jmeno": "",
    "osloveni": "",
    "prijmeni": "",
    "telefon": "",
    "email": "",
    "datum_narozeni": "",
    "spravce": "",
    "budka_cislo": 212,
    "budka_nazev": ""
  }
}