{
  "celkemBudek": 202,
  "osidlenych": 38,
  "spravcuRegistrovano": 154,
  "vycisteno": 100,
  "pribehy": [
    {
      "id": 1,
      "ptak": "Sýkora koňadra",
      "ikona": "konadra",
      "text": "Budka č. 69 u Srubce je obsazena koňadrou třetí rok v řadě! Mláďata se úspěšně vylíhla.",
      "datum": "14. 10. 2024"
    },
    {
      "id": 2,
      "ptak": "Sýkora modřinka",
      "ikona": "modrinka",
      "text": "První modřinka v nové sezóně si vybrala budku č. 37 nedaleko Boskovice.",
      "datum": "28. 3. 2024"
    },
    {
      "id": 3,
      "ptak": "Sýkora parukářka",
      "ikona": "parukarka",
      "text": "Vzácná sýkora parukářka obsadila budku č. 138 u starosty – letos poprvé v projektu!",
      "datum": "12. 5. 2024"
    },
    {
      "id": 4,
      "ptak": "Vrabec domácí",
      "ikona": "vrabec",
      "text": "Po dvou prázdných sezónách se do budky č. 71 nastěhoval vrabec domácí s partnerkou.",
      "datum": "5. 4. 2025"
    },
    {
      "id": 5,
      "ptak": "Sojka obecná",
      "ikona": "sojka",
      "text": "Budka u Sojky (č. 52) žije svému jménu – sojka obecná si ji vybrala za letní domov.",
      "datum": "19. 6. 2024"
    }
  ],
  "partneri": [
    { "nazev": "Město Jevičko", "url": null, "logo": null },
    { "nazev": "Lesy ČR", "url": null, "logo": null },
    { "nazev": "Ornitologický svaz", "url": null, "logo": null },
    { "nazev": "Přátelé přírody", "url": null, "logo": null },
    { "nazev": "VHOS a.s.", "url": null, "logo": "img/partner-vhos.png" },
    { "nazev": "Hutira", "url": null, "logo": null },
    { "nazev": "Stavební expert", "url": null, "logo": null },
    { "nazev": "AVK Litoměřice", "url": null, "logo": null }
  ],
  "navstevnost": {
    "celkem": 14520,
    "dnes": 142,
    "vcera": 285,
    "predvcírem": 210
  }
}
